Metadata-Version: 1.0
Name: lm-decoder
Version: 0.1
Summary: KenLM decoder for Non-Autoregressive Models.
Home-page: UNKNOWN
Author: Jiatao Gu
Author-email: jgu@fb.com
License: UNKNOWN
Platform: UNKNOWN
